pyLHD/LHD_optim.py
pyLHD/OLHD.py
pyLHD/__init__.py
pyLHD/base_designs.py
pyLHD/criteria.py
pyLHD/misc.py
pyLHD/utils.py
pyLHD-0.4.9.dist-info/LICENSE
pyLHD-0.4.9.dist-info/METADATA
pyLHD-0.4.9.dist-info/WHEEL
pyLHD-0.4.9.dist-info/top_level.txt
pyLHD-0.4.9.dist-info/RECORD
