Metadata-Version: 2.1
Name: pyLHD
Version: 0.4.9
Summary: Latin Hypercube Designs for Python
Home-page: https://github.com/toledo60/pyLHD
Author: Jose Toledo
Author-email: toledo60@protonmail.com
License: UNKNOWN
Project-URL: Bug Tracker, https://github.com/toledo60/pyLHD/issues
Platform: UNKNOWN
Classifier: Programming Language :: Python :: 3
Classifier: License :: OSI Approved :: MIT License
Classifier: Operating System :: OS Independent
Requires-Python: >=3.6
License-File: LICENSE
Requires-Dist: numpy
